{
  "version": "7",
  "dialect": "mysql",
  "entries": [
    {
      "idx": 0,
      "version": "5",
      "when": 1765103037338,
      "tag": "0000_tough_captain_flint",
      "breakpoints": true
    },
    {
      "idx": 1,
      "version": "5",
      "when": 1765103234391,
      "tag": "0001_absurd_slipstream",
      "breakpoints": true
    },
    {
      "idx": 2,
      "version": "5",
      "when": 1765105790353,
      "tag": "0002_flat_iron_fist",
      "breakpoints": true
    },
    {
      "idx": 3,
      "version": "5",
      "when": 1765129460221,
      "tag": "0003_acoustic_echo",
      "breakpoints": true
    },
    {
      "idx": 4,
      "version": "5",
      "when": 1765136536434,
      "tag": "0004_tricky_valeria_richards",
      "breakpoints": true
    },
    {
      "idx": 5,
      "version": "5",
      "when": 1765136635606,
      "tag": "0005_careful_grey_gargoyle",
      "breakpoints": true
    },
    {
      "idx": 6,
      "version": "5",
      "when": 1765137174562,
      "tag": "0006_brown_jasper_sitwell",
      "breakpoints": true
    }
  ]
}